karton_unpacker-1.1.1-nspkg.pth
karton/unpacker/__init__.py
karton/unpacker/__main__.py
karton/unpacker/__version__.py
karton/unpacker/unpacker.py
karton_unpacker-1.1.1.dist-info/LICENSE
karton_unpacker-1.1.1.dist-info/METADATA
karton_unpacker-1.1.1.dist-info/WHEEL
karton_unpacker-1.1.1.dist-info/entry_points.txt
karton_unpacker-1.1.1.dist-info/namespace_packages.txt
karton_unpacker-1.1.1.dist-info/top_level.txt
karton_unpacker-1.1.1.dist-info/RECORD
