Metadata-Version: 2.1
Name: karton-unpacker
Version: 1.1.1
Summary: A modular Karton Framework service that unpacks common packers like UPX, MPress and others using the Qilling Framework.
Home-page: UNKNOWN
License: UNKNOWN
Platform: UNKNOWN
Classifier: Programming Language :: Python
Classifier: Operating System :: OS Independent
Requires-Dist: hexdump (==3.3)
Requires-Dist: karton-core (==4.2.0)
Requires-Dist: pefile (==2019.4.18)
Requires-Dist: qiling (==1.2.3)
Requires-Dist: yara-python (==4.0.5)
